[
  {
    "lookupId": 51533,
    "code": 80333,
    "jarCode": "123033512",
    "name": "MAXIMA LT, UAB",
    "shortname": "MAXIMA LT, UAB",
    "month": 201701,
    "avgWage": 547.7,
    "avgWage2": null,
    "numInsured": 14621,
    "numInsured2": 0,
    "tax": 3299667.48,
    "ecoActName": "Mažmeninė prekyba nespecializuotose parduotuvėse, kuriose vyrauja maistas, gėrimai ir tabakas",
    "ecoActCode": 471100.0,
    "municipality": "Vilniaus m. sav."
  },
  {
    "lookupId": 51533,
    "code": 80333,
    "jarCode": "123033512",
    "name": "MAXIMA LT, UAB",
    "shortname": "MAXIMA LT, UAB",
    "month": 201702,
    "avgWage": 507.69,
    "avgWage2": null,
    "numInsured": 14441,
    "numInsured2": 0,
    "tax": 3024068.81,
    "ecoActName": "Mažmeninė prekyba nespecializuotose parduotuvėse, kuriose vyrauja maistas, gėrimai ir tabakas",
    "ecoActCode": 471100.0,
    "municipality": "Vilniaus m. sav."
  },
  {
    "lookupId": 51533,
    "code": 80333,
    "jarCode": "123033512",
    "name": "MAXIMA LT, UAB",
    "shortname": "MAXIMA LT, UAB",
    "month": 201703,
    "avgWage": 554.72,
    "avgWage2": null,
    "numInsured": 14633,
    "numInsured2": 0,
    "tax": 3347693.81,
    "ecoActName": "Mažmeninė prekyba nespecializuotose parduotuvėse, kuriose vyrauja maistas, gėrimai ir tabakas",
    "ecoActCode": 471100.0,
    "municipality": "Vilniaus m. sav."
  },
  {
    "lookupId": 51533,
    "code": 80333,
    "jarCode": "123033512",
    "name": "MAXIMA LT, UAB",
    "shortname": "MAXIMA LT, UAB",
    "month": 201704,
    "avgWage": 587.35,
    "avgWage2": null,
    "numInsured": 14513,
    "numInsured2": 0,
    "tax": 3517226.47,
    "ecoActName": "Mažmeninė prekyba nespecializuotose parduotuvėse, kuriose vyrauja maistas, gėrimai ir tabakas",
    "ecoActCode": 471100.0,
    "municipality": "Vilniaus m. sav."
  },
  {
    "lookupId": 51533,
    "code": 80333,
    "jarCode": "123033512",
    "name": "MAXIMA LT, UAB",
    "shortname": "MAXIMA LT, UAB",
    "month": 201705,
    "avgWage": 572.41,
    "avgWage2": null,
    "numInsured": 14654,
    "numInsured2": 0,
    "tax": 3460356.89,
    "ecoActName": "Mažmeninė prekyba nespecializuotose parduotuvėse, kuriose vyrauja maistas, gėrimai ir tabakas",
    "ecoActCode": 471100.0,
    "municipality": "Vilniaus m. sav."
  },
  {
    "lookupId": 51533,
    "code": 80333,
    "jarCode": "123033512",
    "name": "MAXIMA LT, UAB",
    "shortname": "MAXIMA LT, UAB",
    "month": 201706,
    "avgWage": 552.12,
    "avgWage2": null,
    "numInsured": 15291,
    "numInsured2": 0,
    "tax": 3481276.0,
    "ecoActName": "Mažmeninė prekyba nespecializuotose parduotuvėse, kuriose vyrauja maistas, gėrimai ir tabakas",
    "ecoActCode": 471100.0,
    "municipality": "Vilniaus m. sav."
  },
  {
    "lookupId": 51533,
    "code": 80333,
    "jarCode": "123033512",
    "name": "MAXIMA LT, UAB",
    "shortname": "MAXIMA LT, UAB",
    "month": 201707,
    "avgWage": 585.36,
    "avgWage2": null,
    "numInsured": 15375,
    "numInsured2": 0,
    "tax": 3717735.74,
    "ecoActName": "Mažmeninė prekyba nespecializuotose parduotuvėse, kuriose vyrauja maistas, gėrimai ir tabakas",
    "ecoActCode": 471100.0,
    "municipality": "Vilniaus m. sav."
  },
  {
    "lookupId": 51533,
    "code": 80333,
    "jarCode": "123033512",
    "name": "MAXIMA LT, UAB",
    "shortname": "MAXIMA LT, UAB",
    "month": 201708,
    "avgWage": 566.72,
    "avgWage2": null,
    "numInsured": 15163,
    "numInsured2": 0,
    "tax": 3549478.78,
    "ecoActName": "Mažmeninė prekyba nespecializuotose parduotuvėse, kuriose vyrauja maistas, gėrimai ir tabakas",
    "ecoActCode": 471100.0,
    "municipality": "Vilniaus m. sav."
  },
  {
    "lookupId": 51533,
    "code": 80333,
    "jarCode": "123033512",
    "name": "MAXIMA LT, UAB",
    "shortname": "MAXIMA LT, UAB",
    "month": 201709,
    "avgWage": 534.95,
    "avgWage2": null,
    "numInsured": 14414,
    "numInsured2": 0,
    "tax": 3183000.99,
    "ecoActName": "Mažmeninė prekyba nespecializuotose parduotuvėse, kuriose vyrauja maistas, gėrimai ir tabakas",
    "ecoActCode": 471100.0,
    "municipality": "Vilniaus m. sav."
  },
  {
    "lookupId": 51533,
    "code": 80333,
    "jarCode": "123033512",
    "name": "MAXIMA LT, UAB",
    "shortname": "MAXIMA LT, UAB",
    "month": 201710,
    "avgWage": 566.63,
    "avgWage2": null,
    "numInsured": 14463,
    "numInsured2": 0,
    "tax": 3384356.9,
    "ecoActName": "Mažmeninė prekyba nespecializuotose parduotuvėse, kuriose vyrauja maistas, gėrimai ir tabakas",
    "ecoActCode": 471100.0,
    "municipality": "Vilniaus m. sav."
  },
  {
    "lookupId": 51533,
    "code": 80333,
    "jarCode": "123033512",
    "name": "MAXIMA LT, UAB",
    "shortname": "MAXIMA LT, UAB",
    "month": 201711,
    "avgWage": 551.71,
    "avgWage2": null,
    "numInsured": 14698,
    "numInsured2": 0,
    "tax": 3346394.79,
    "ecoActName": "Mažmeninė prekyba nespecializuotose parduotuvėse, kuriose vyrauja maistas, gėrimai ir tabakas",
    "ecoActCode": 471100.0,
    "municipality": "Vilniaus m. sav."
  },
  {
    "lookupId": 51533,
    "code": 80333,
    "jarCode": "123033512",
    "name": "MAXIMA LT, UAB",
    "shortname": "MAXIMA LT, UAB",
    "month": 201712,
    "avgWage": 579.99,
    "avgWage2": null,
    "numInsured": 14699,
    "numInsured2": 0,
    "tax": 3517754.54,
    "ecoActName": "Mažmeninė prekyba nespecializuotose parduotuvėse, kuriose vyrauja maistas, gėrimai ir tabakas",
    "ecoActCode": 471100.0,
    "municipality": "Vilniaus m. sav."
  },
  {
    "lookupId": 51533,
    "code": 80333,
    "jarCode": "123033512",
    "name": "MAXIMA LT, UAB",
    "shortname": "MAXIMA LT, UAB",
    "month": 201801,
    "avgWage": 597.68,
    "avgWage2": null,
    "numInsured": 14602,
    "numInsured2": 0,
    "tax": 3605054.79,
    "ecoActName": "Mažmeninė prekyba nespecializuotose parduotuvėse, kuriose vyrauja maistas, gėrimai ir tabakas",
    "ecoActCode": 471100.0,
    "municipality": "Vilniaus m. sav."
  },
  {
    "lookupId": 51533,
    "code": 80333,
    "jarCode": "123033512",
    "name": "MAXIMA LT, UAB",
    "shortname": "MAXIMA LT, UAB",
    "month": 201802,
    "avgWage": 519.95,
    "avgWage2": null,
    "numInsured": 14390,
    "numInsured2": 0,
    "tax": 3090442.5,
    "ecoActName": "Mažmeninė prekyba nespecializuotose parduotuvėse, kuriose vyrauja maistas, gėrimai ir tabakas",
    "ecoActCode": 471100.0,
    "municipality": "Vilniaus m. sav."
  },
  {
    "lookupId": 51533,
    "code": 80333,
    "jarCode": "123033512",
    "name": "MAXIMA LT, UAB",
    "shortname": "MAXIMA LT, UAB",
    "month": 201803,
    "avgWage": 576.96,
    "avgWage2": null,
    "numInsured": 14497,
    "numInsured2": 0,
    "tax": 3455218.39,
    "ecoActName": "Mažmeninė prekyba nespecializuotose parduotuvėse, kuriose vyrauja maistas, gėrimai ir tabakas",
    "ecoActCode": 471100.0,
    "municipality": "Vilniaus m. sav."
  },
  {
    "lookupId": 51533,
    "code": 80333,
    "jarCode": "123033512",
    "name": "MAXIMA LT, UAB",
    "shortname": "MAXIMA LT, UAB",
    "month": 201804,
    "avgWage": 576.26,
    "avgWage2": null,
    "numInsured": 14441,
    "numInsured2": 0,
    "tax": 3437089.81,
    "ecoActName": "Mažmeninė prekyba nespecializuotose parduotuvėse, kuriose vyrauja maistas, gėrimai ir tabakas",
    "ecoActCode": 471100.0,
    "municipality": "Vilniaus m. sav."
  },
  {
    "lookupId": 51533,
    "code": 80333,
    "jarCode": "123033512",
    "name": "MAXIMA LT, UAB",
    "shortname": "MAXIMA LT, UAB",
    "month": 201805,
    "avgWage": 615.95,
    "avgWage2": null,
    "numInsured": 14524,
    "numInsured2": 0,
    "tax": 3695595.25,
    "ecoActName": "Mažmeninė prekyba nespecializuotose parduotuvėse, kuriose vyrauja maistas, gėrimai ir tabakas",
    "ecoActCode": 471100.0,
    "municipality": "Vilniaus m. sav."
  },
  {
    "lookupId": 51533,
    "code": 80333,
    "jarCode": "123033512",
    "name": "MAXIMA LT, UAB",
    "shortname": "MAXIMA LT, UAB",
    "month": 201806,
    "avgWage": 581.45,
    "avgWage2": null,
    "numInsured": 14954,
    "numInsured2": 0,
    "tax": 3592844.69,
    "ecoActName": "Mažmeninė prekyba nespecializuotose parduotuvėse, kuriose vyrauja maistas, gėrimai ir tabakas",
    "ecoActCode": 471100.0,
    "municipality": "Vilniaus m. sav."
  },
  {
    "lookupId": 51533,
    "code": 80333,
    "jarCode": "123033512",
    "name": "MAXIMA LT, UAB",
    "shortname": "MAXIMA LT, UAB",
    "month": 201807,
    "avgWage": 624.24,
    "avgWage2": null,
    "numInsured": 15028,
    "numInsured2": 0,
    "tax": 3876978.94,
    "ecoActName": "Mažmeninė prekyba nespecializuotose parduotuvėse, kuriose vyrauja maistas, gėrimai ir tabakas",
    "ecoActCode": 471100.0,
    "municipality": "Vilniaus m. sav."
  },
  {
    "lookupId": 51533,
    "code": 80333,
    "jarCode": "123033512",
    "name": "MAXIMA LT, UAB",
    "shortname": "MAXIMA LT, UAB",
    "month": 201808,
    "avgWage": 600.76,
    "avgWage2": null,
    "numInsured": 14747,
    "numInsured2": 0,
    "tax": 3661790.65,
    "ecoActName": "Mažmeninė prekyba nespecializuotose parduotuvėse, kuriose vyrauja maistas, gėrimai ir tabakas",
    "ecoActCode": 471100.0,
    "municipality": "Vilniaus m. sav."
  },
  {
    "lookupId": 51533,
    "code": 80333,
    "jarCode": "123033512",
    "name": "MAXIMA LT, UAB",
    "shortname": "MAXIMA LT, UAB",
    "month": 201809,
    "avgWage": 572.37,
    "avgWage2": null,
    "numInsured": 13916,
    "numInsured2": 0,
    "tax": 3290035.24,
    "ecoActName": "Mažmeninė prekyba nespecializuotose parduotuvėse, kuriose vyrauja maistas, gėrimai ir tabakas",
    "ecoActCode": 471100.0,
    "municipality": "Vilniaus m. sav."
  },
  {
    "lookupId": 51533,
    "code": 80333,
    "jarCode": "123033512",
    "name": "MAXIMA LT, UAB",
    "shortname": "MAXIMA LT, UAB",
    "month": 201810,
    "avgWage": 616.09,
    "avgWage2": null,
    "numInsured": 13873,
    "numInsured2": 0,
    "tax": 3530082.47,
    "ecoActName": "Mažmeninė prekyba nespecializuotose parduotuvėse, kuriose vyrauja maistas, gėrimai ir tabakas",
    "ecoActCode": 471100.0,
    "municipality": "Vilniaus m. sav."
  },
  {
    "lookupId": 51533,
    "code": 80333,
    "jarCode": "123033512",
    "name": "MAXIMA LT, UAB",
    "shortname": "MAXIMA LT, UAB",
    "month": 201811,
    "avgWage": 594.99,
    "avgWage2": null,
    "numInsured": 13781,
    "numInsured2": 0,
    "tax": 3387214.59,
    "ecoActName": "Mažmeninė prekyba nespecializuotose parduotuvėse, kuriose vyrauja maistas, gėrimai ir tabakas",
    "ecoActCode": 471100.0,
    "municipality": "Vilniaus m. sav."
  },
  {
    "lookupId": 51533,
    "code": 80333,
    "jarCode": "123033512",
    "name": "MAXIMA LT, UAB",
    "shortname": "MAXIMA LT, UAB",
    "month": 201812,
    "avgWage": 662.7,
    "avgWage2": null,
    "numInsured": 13787,
    "numInsured2": 0,
    "tax": 3774595.11,
    "ecoActName": "Mažmeninė prekyba nespecializuotose parduotuvėse, kuriose vyrauja maistas, gėrimai ir tabakas",
    "ecoActCode": 471100.0,
    "municipality": "Vilniaus m. sav."
  },
  {
    "lookupId": 51533,
    "code": 80333,
    "jarCode": "123033512",
    "name": "MAXIMA LT, UAB",
    "shortname": "MAXIMA LT, UAB",
    "month": 201901,
    "avgWage": 846.93,
    "avgWage2": null,
    "numInsured": 13865,
    "numInsured2": 0,
    "tax": 2730349.0,
    "ecoActName": "Mažmeninė prekyba nespecializuotose parduotuvėse, kuriose vyrauja maistas, gėrimai ir tabakas",
    "ecoActCode": 471100.0,
    "municipality": "Vilniaus m. sav."
  },
  {
    "lookupId": 51533,
    "code": 80333,
    "jarCode": "123033512",
    "name": "MAXIMA LT, UAB",
    "shortname": "MAXIMA LT, UAB",
    "month": 201902,
    "avgWage": 768.25,
    "avgWage2": null,
    "numInsured": 13790,
    "numInsured2": 0,
    "tax": 2462699.58,
    "ecoActName": "Mažmeninė prekyba nespecializuotose parduotuvėse, kuriose vyrauja maistas, gėrimai ir tabakas",
    "ecoActCode": 471100.0,
    "municipality": "Vilniaus m. sav."
  },
  {
    "lookupId": 51533,
    "code": 80333,
    "jarCode": "123033512",
    "name": "MAXIMA LT, UAB",
    "shortname": "MAXIMA LT, UAB",
    "month": 201903,
    "avgWage": 825.99,
    "avgWage2": null,
    "numInsured": 13888,
    "numInsured2": 0,
    "tax": 2664518.62,
    "ecoActName": "Mažmeninė prekyba nespecializuotose parduotuvėse, kuriose vyrauja maistas, gėrimai ir tabakas",
    "ecoActCode": 471100.0,
    "municipality": "Vilniaus m. sav."
  },
  {
    "lookupId": 51533,
    "code": 80333,
    "jarCode": "123033512",
    "name": "MAXIMA LT, UAB",
    "shortname": "MAXIMA LT, UAB",
    "month": 201904,
    "avgWage": 866.9,
    "avgWage2": null,
    "numInsured": 13909,
    "numInsured2": 0,
    "tax": 2798164.59,
    "ecoActName": "Mažmeninė prekyba nespecializuotose parduotuvėse, kuriose vyrauja maistas, gėrimai ir tabakas",
    "ecoActCode": 471100.0,
    "municipality": "Vilniaus m. sav."
  },
  {
    "lookupId": 51533,
    "code": 80333,
    "jarCode": "123033512",
    "name": "MAXIMA LT, UAB",
    "shortname": "MAXIMA LT, UAB",
    "month": 201905,
    "avgWage": 869.79,
    "avgWage2": null,
    "numInsured": 14070,
    "numInsured2": 0,
    "tax": 2830891.98,
    "ecoActName": "Mažmeninė prekyba nespecializuotose parduotuvėse, kuriose vyrauja maistas, gėrimai ir tabakas",
    "ecoActCode": 471100.0,
    "municipality": "Vilniaus m. sav."
  },
  {
    "lookupId": 51533,
    "code": 80333,
    "jarCode": "123033512",
    "name": "MAXIMA LT, UAB",
    "shortname": "MAXIMA LT, UAB",
    "month": 201906,
    "avgWage": 821.75,
    "avgWage2": null,
    "numInsured": 14406,
    "numInsured2": 0,
    "tax": 2722935.57,
    "ecoActName": "Mažmeninė prekyba nespecializuotose parduotuvėse, kuriose vyrauja maistas, gėrimai ir tabakas",
    "ecoActCode": 471100.0,
    "municipality": "Vilniaus m. sav."
  },
  {
    "lookupId": 51533,
    "code": 80333,
    "jarCode": "123033512",
    "name": "MAXIMA LT, UAB",
    "shortname": "MAXIMA LT, UAB",
    "month": 201907,
    "avgWage": 883.05,
    "avgWage2": null,
    "numInsured": 14669,
    "numInsured2": 0,
    "tax": 2976992.95,
    "ecoActName": "Mažmeninė prekyba nespecializuotose parduotuvėse, kuriose vyrauja maistas, gėrimai ir tabakas",
    "ecoActCode": 471100.0,
    "municipality": "Vilniaus m. sav."
  },
  {
    "lookupId": 51533,
    "code": 80333,
    "jarCode": "123033512",
    "name": "MAXIMA LT, UAB",
    "shortname": "MAXIMA LT, UAB",
    "month": 201908,
    "avgWage": 849.11,
    "avgWage2": null,
    "numInsured": 14446,
    "numInsured2": 1,
    "tax": 2821225.83,
    "ecoActName": "Mažmeninė prekyba nespecializuotose parduotuvėse, kuriose vyrauja maistas, gėrimai ir tabakas",
    "ecoActCode": 471100.0,
    "municipality": "Vilniaus m. sav."
  },
  {
    "lookupId": 51533,
    "code": 80333,
    "jarCode": "123033512",
    "name": "MAXIMA LT, UAB",
    "shortname": "MAXIMA LT, UAB",
    "month": 201909,
    "avgWage": 810.74,
    "avgWage2": null,
    "numInsured": 13855,
    "numInsured2": 0,
    "tax": 2583909.08,
    "ecoActName": "Mažmeninė prekyba nespecializuotose parduotuvėse, kuriose vyrauja maistas, gėrimai ir tabakas",
    "ecoActCode": 471100.0,
    "municipality": "Vilniaus m. sav."
  }
]